<?xml version="1.0" encoding="UTF-8"?>
<persistence xmlns="http://xmlns.jcp.org/xml/ns/persistence" version="2.1">
    <persistence-unit name="PersistenceUnitHibernateH2">
        <class>entities.CompletedTask</class>
        <class>entities.Course</class>
        <class>entities.StudentsGroup</class>
        <class>entities.Student</class>
        <class>entities.Task</class>
        <class>entities.Teacher</class>
        <class>entities.University</class>
        <properties>
            <property name="hibernate.connection.url" value="jdbc:h2:file:C:/Users/Augustinas/OneDrive/javaProjects/H2_DB/sample;"/>
            <property name="hibernate.connection.driver_class" value="org.h2.Driver"/>
            <property name="hibernate.connection.username" value="sa"/>
            <property name="hibernate.connection.password" value=""/>
            <property name="hibernate.archive.autodetection" value="class"/>
            <property name="hibernate.show_sql" value="true"/>
            <property name="hibernate.format_sql" value="true"/>
            <property name="hibernate.hbm2ddl.auto" value="update"/>
        </properties>
    </persistence-unit>
</persistence>
